setup.py
bolton_distributions/Binomialdistribution.py
bolton_distributions/Gaussiandistribution.py
bolton_distributions/Generaldistribution.py
bolton_distributions/__init__.py
bolton_distributions.egg-info/PKG-INFO
bolton_distributions.egg-info/SOURCES.txt
bolton_distributions.egg-info/dependency_links.txt
bolton_distributions.egg-info/not-zip-safe
bolton_distributions.egg-info/top_level.txt